tcrsift/__init__.py
tcrsift/annotate.py
tcrsift/assemble.py
tcrsift/cli.py
tcrsift/clonotype.py
tcrsift/config.py
tcrsift/data.py
tcrsift/filter.py
tcrsift/gex.py
tcrsift/loader.py
tcrsift/mnemonic.py
tcrsift/model.py
tcrsift/phenotype.py
tcrsift/plots.py
tcrsift/qc.py
tcrsift/sample_sheet.py
tcrsift/sct.py
tcrsift/til.py
tcrsift/unify.py
tcrsift/validation.py
tcrsift/version.py
tcrsift-0.2.2.dist-info/licenses/LICENSE
tcrsift-0.2.2.dist-info/METADATA
tcrsift-0.2.2.dist-info/WHEEL
tcrsift-0.2.2.dist-info/entry_points.txt
tcrsift-0.2.2.dist-info/top_level.txt
tcrsift-0.2.2.dist-info/RECORD
