Metadata-Version: 2.4
Name: tcrsift
Version: 0.2.2
Summary: T-cell receptor selection for TCR-T studies from antigen specific culture and scRNA/VDJ sequencing
Author-email: Alex Rubinsteyn <alex.rubinsteyn@unc.edu>
Project-URL: Homepage, https://github.com/pirl-unc/tcrsift
Project-URL: Documentation, https://pirl-unc.github.io/tcrsift/
Project-URL: Bug Tracker, https://github.com/pirl-unc/tcrsift/issues
Classifier: Programming Language :: Python :: 3
Classifier: Programming Language :: Python :: 3.9
Classifier: Programming Language :: Python :: 3.10
Classifier: Programming Language :: Python :: 3.11
Classifier: Programming Language :: Python :: 3.12
Classifier: Programming Language :: Python :: Implementation :: CPython
Classifier: Environment :: Console
Classifier: Operating System :: OS Independent
Classifier: Intended Audience :: Science/Research
Classifier: License :: OSI Approved :: Apache Software License
Classifier: Topic :: Scientific/Engineering :: Bio-Informatics
Requires-Python: >=3.9
License-File: LICENSE
Requires-Dist: numpy<2.0.0,>=1.14.0
Requires-Dist: pandas<3.0.0,>=2.1.4
Requires-Dist: scanpy<2.0.0,>=1.10.2
Requires-Dist: anndata<1.0.0,>=0.10.0
Requires-Dist: matplotlib<4.0.0,>=3.7.0
Requires-Dist: seaborn<1.0.0,>=0.13
Requires-Dist: pyensembl<3.0.0,>=2.0.0
Requires-Dist: statsmodels<1.0.0,>=0.14.0
Requires-Dist: reportlab<5.0.0,>=4.0.0
Requires-Dist: pdfkit
Requires-Dist: pyyaml<7.0,>=6.0
Requires-Dist: openpyxl<4.0.0,>=3.0.0
Requires-Dist: tqdm<5.0.0,>=4.60.0
Provides-Extra: dev
Requires-Dist: pytest>=7.0.0; extra == "dev"
Requires-Dist: pytest-cov>=4.0.0; extra == "dev"
Requires-Dist: ruff>=0.1.0; extra == "dev"
Requires-Dist: pylint>=3.0.0; extra == "dev"
Provides-Extra: docs
Requires-Dist: mkdocs>=1.5.0; extra == "docs"
Requires-Dist: mkdocs-material>=9.0.0; extra == "docs"
Requires-Dist: mkdocstrings[python]>=0.24.0; extra == "docs"
Requires-Dist: pymdown-extensions>=10.0.0; extra == "docs"
Dynamic: license-file
